MRN/__init__.py
MRN/scale.py
MRN-0.1.1.dist-info/METADATA
MRN-0.1.1.dist-info/WHEEL
MRN-0.1.1.dist-info/top_level.txt
MRN-0.1.1.dist-info/RECORD
